Metadata-Version: 2.4
Name: soda-conan-server
Version: 2025.1.27.0
Summary: soda's conan server
Project-URL: Repository, https://github.com/soda92/conan/tree/my-server
License-File: LICENSE.md
Requires-Python: >=3.10
Requires-Dist: bottle>=0.13.2
Requires-Dist: colorama>=0.4.6
Requires-Dist: fasteners>=0.19
Requires-Dist: jinja2>=3.1.5
Requires-Dist: patch-ng>=1.18.1
Requires-Dist: pluginbase>=1.0.1
Requires-Dist: pyjwt>=2.10.1
Requires-Dist: python-dateutil>=2.9.0.post0
Requires-Dist: pyyaml>=6.0.2
Requires-Dist: urllib3>=2.3.0
